MANIFEST.in
README.rst
setup.py
image_diet/__init__.py
image_diet/default.yml
image_diet/storage.py
image_diet2.egg-info/PKG-INFO
image_diet2.egg-info/SOURCES.txt
image_diet2.egg-info/dependency_links.txt
image_diet2.egg-info/not-zip-safe
image_diet2.egg-info/requires.txt
image_diet2.egg-info/top_level.txt